tools_fjh/__init__.py
tools_fjh/tools_fjh.py
tools_fjh-0.1.5.dist-info/licenses/LICENSE
tools_fjh-0.1.5.dist-info/METADATA
tools_fjh-0.1.5.dist-info/WHEEL
tools_fjh-0.1.5.dist-info/top_level.txt
tools_fjh-0.1.5.dist-info/RECORD
