Metadata-Version: 2.4
Name: tools_fjh
Version: 0.1.5
Summary: 装饰器工具集
Home-page: https://github.com/cxfjh/DecoTools
Author: cxfjh
Author-email: 2449579731@qq.com
Keywords: deco tools decorator,装饰器,工具集
Classifier: Programming Language :: Python :: 3
Classifier: License :: OSI Approved :: MIT License
Classifier: Operating System :: OS Independent
Classifier: Topic :: Database
Classifier: Topic :: Software Development :: Libraries
Requires-Python: >=3.6
License-File: LICENSE
Dynamic: author
Dynamic: author-email
Dynamic: classifier
Dynamic: description
Dynamic: description-content-type
Dynamic: home-page
Dynamic: keywords
Dynamic: license-file
Dynamic: requires-python
Dynamic: summary
